pyndiff/__init__.py
pyndiff/__main__.py
pyndiff/core.py
pyndiff/ndiff.py
pyndiff-1.0.2.dist-info/LICENSE
pyndiff-1.0.2.dist-info/METADATA
pyndiff-1.0.2.dist-info/WHEEL
pyndiff-1.0.2.dist-info/entry_points.txt
pyndiff-1.0.2.dist-info/top_level.txt
pyndiff-1.0.2.dist-info/RECORD
