Metadata-Version: 2.1
Name: pyndiff
Version: 1.0.2
Summary: Generate human-readable ndiff output when comparing 2 Nmap XML scan files.
Home-page: https://github.com/rackerlabs/pyndiff
Author: Brennon Thomas
Author-email: info@opsdisk.com
License: License is Apache License Version 2.0
Keywords: python Nmap ndiff xml compare scans
Platform: UNKNOWN
Requires-Python: >=3.6
Requires-Dist: xmljson (>=0.2.0)
